__init__.py
difflib.py
extended_difflib.py
names_matcher.py
plurals.csv
synonyms.csv
namecompare-0.0.7.dist-info/LICENSE
namecompare-0.0.7.dist-info/METADATA
namecompare-0.0.7.dist-info/WHEEL
namecompare-0.0.7.dist-info/top_level.txt
namecompare-0.0.7.dist-info/RECORD
