Metadata-Version: 2.1
Name: namecompare
Version: 0.0.7
Summary: Ratio calculator between names - especially of elements (variables, classes and methods) in a program code.
Home-page: https://github.com/AutoPurchase/name_compare
Author: Moshe Munk
Author-email: moshe.munk@mail.huji.ac.il
Classifier: Programming Language :: Python :: 3
Classifier: License :: OSI Approved :: MIT License
Classifier: Operating System :: OS Independent
Requires-Python: >=3.8
License-File: LICENSE
Requires-Dist: strsimpy (>=0.2.1)
